scipioninstaller/__init__.py
scipioninstaller/__main__.py
scipioninstaller/installer.py
scipioninstaller/launchers.py
scipion_installer-2.1.dist-info/LICENSE
scipion_installer-2.1.dist-info/METADATA
scipion_installer-2.1.dist-info/WHEEL
scipion_installer-2.1.dist-info/entry_points.txt
scipion_installer-2.1.dist-info/top_level.txt
scipion_installer-2.1.dist-info/RECORD
