Metadata-Version: 2.1
Name: scipion-installer
Version: 2.1
Summary: Installs scipion 3 creating a virtual environment for it anc creates a launcher.
Author-email: Pablo Conesa <pconesa@cnb.csic.es>
License: GNU General Public License v3 (GPLv3)
Project-URL: Homepage, https://github.com/scipion-em/scipion-installer
Project-URL: Issues, https://github.com/scipion-em/scipion-installer/issues
Keywords: scipion cryoem imageprocessing scipion-3.0
Requires-Python: >=2.7
License-File: LICENSE
Requires-Dist: virtualenv
